Metadata-Version: 2.1
Name: pulumi-metabase
Version: 0.0.3
Summary: UNKNOWN
Home-page: UNKNOWN
License: UNKNOWN
Platform: UNKNOWN
